spc/__init__.py
spc/global_fun.py
spc/spc.py
spc/sub.py
pyfasma_spc-0.4.2.dist-info/LICENSE
pyfasma_spc-0.4.2.dist-info/METADATA
pyfasma_spc-0.4.2.dist-info/WHEEL
pyfasma_spc-0.4.2.dist-info/RECORD
