Metadata-Version: 2.1
Name: pyfasma-spc
Version: 0.4.2
Summary: A Python package for handling SPC files
Home-page: https://github.com/lepa22/pyfasma-spc
License: GNU General Public License v3 (GPLv3)
Keywords: scientific,SPC,spectra,data analysis
Author: Rohan Isaac
Author-email: rohan_isaac@yahoo.com
Requires-Python: >=3.12,<4.0
Classifier: Development Status :: 4 - Beta
Classifier: Intended Audience :: Science/Research
Classifier: License :: OSI Approved :: GNU General Public License v3 (GPLv3)
Classifier: License :: Other/Proprietary License
Classifier: Programming Language :: Python :: 3
Classifier: Programming Language :: Python :: 3.12
Classifier: Programming Language :: Python :: 3.5
Classifier: Topic :: Scientific/Engineering :: Chemistry
Requires-Dist: matplotlib (>=3.8,<4.0)
Requires-Dist: numpy (>=2.0,<3.0)
Project-URL: Repository, https://github.com/lepa22/pyfasma-spc
